Workbook
Name StartingBalance: Resumo!$L$8

Sheet Resumo
B2: PRIMEIROS PASSOS | I2: OBSERVAÇÃO
B3: Defina seu saldo inicial na célula L8 e personalize as categorias e os valores das despesas planejadas nas tabelas "Renda" e "Despesas" abaixo. | I3: Só edite as células destacadas.
I4: Tente não alterar as células que contêm uma fórmula.
B5: Quando você digitar dados na guia "Transações", esta página será atualizada automaticamente para mostrar um resumo das suas despesas no mês.
B8: Orçamento mensal | J8: Saldo inicial:
D12: =IFERROR(__xludf.DUMMYFUNCTION("SPARKLINE(D17,{""charttype"",""column"";""ymin"", 0; ""ymax"",MAX(D17:E17);""firstcolor"",""#334960""})"),"") | E12: =IFERROR(__xludf.DUMMYFUNCTION("SPARKLINE(E17,{""charttype"",""column"";""ymin"", 0; ""ymax"",max(D17:E17);""firstcolor"",""#f46524""})"),"")
I13: =iferror(E17/D17-1, "")
I14: =if(I13 < 0, "Redução da economia total", "Aumento da economia total") -> Aumento da economia total
I15: =iferror(E17-D17, 0) -> 11318
D16: SALDO INICIAL | E16: SALDO FINAL | I16: =if(J15<0, "Despesa do mês", "Economia do mês") -> Economia do mês
D17: =if(isblank(L8),0,L8) -> 0 | E17: =D17+(I22-C22) -> 11318
B20: Despesas | H20: Renda
B21: Planejado | C21: =D26 -> 13552.075 | D21: =IFERROR(__xludf.DUMMYFUNCTION("SPARKLINE(C21,{""charttype"",""bar"";""max"",max(C21:C22);""color1"",""#AEB7C0""})"),"") | H21: Planejado | I21: =J26 -> 13967 | J21: =IFERROR(__xludf.DUMMYFUNCTION("SPARKLINE(I21,{""charttype"",""bar"";""max"",max(I21:I22);""color1"",""#AEB7C0""})"),"")
B22: Real | C22: =E26 -> 1100 | D22: =IFERROR(__xludf.DUMMYFUNCTION("SPARKLINE(C22,{""charttype"",""bar"";""max"",max(C21:C22);""color1"",""#334960""})"),"") | H22: Real | I22: =K26 -> 12418 | J22: =IFERROR(__xludf.DUMMYFUNCTION("SPARKLINE(I22,{""charttype"",""bar"";""max"",max(I21:I22);""color1"",""#334960""})"),"")
B24: Despesas | H24: Renda
D25: Planejado | E25: Real | F25: Diferença | J25: Planejado | K25: Real | L25: Diferença
B26: Totais | D26: =sum(D27:D43) -> 13552.075 | E26: =sum(E27:E43) -> 1100 | F26: =sum(F27:F43) -> 12452.075 | H26: Totais | J26: =sum(J27:J43) -> 13967 | K26: =sum(K27:K43) -> 12418 | L26: =sum(L27:L43) -> -1549
E27: =if(isblank($B27), "", sumif('Transações'!$E:$E,$B27,'Transações'!$C:$C)) | F27: =if(isblank($B27), "", D27-E27) | K27: =if(isblank($H27), "", sumif('Transações'!$J:$J,$H27,'Transações'!$H:$H)) | L27: =if(isblank($H27), "", K27-J27)
B28: Alimentação | D28: 3000 | E28: =if(isblank($B28), "", sumif('Transações'!$E:$E,$B28,'Transações'!$C:$C)) -> 0 | F28: =if(isblank($B28), "", D28-E28) -> 3000 | H28: Vale Alimentação | J28: 1549 | K28: =if(isblank($H28), "", sumif('Transações'!$J:$J,$H28,'Transações'!$H:$H)) -> 0 | L28: =if(isblank($H28), "", K28-J28) -> -1549
B29: Água | D29: 200 | E29: =if(isblank($B29), "", sumif('Transações'!$E:$E,$B29,'Transações'!$C:$C)) -> 0 | F29: =if(isblank($B29), "", D29-E29) -> 200 | H29: Pagamento | J29: 12418 | K29: =if(isblank($H29), "", sumif('Transações'!$J:$J,$H29,'Transações'!$H:$H)) -> 12418 | L29: =if(isblank($H29), "", K29-J29) -> 0
B30: Luz | D30: 300 | E30: =if(isblank($B30), "", sumif('Transações'!$E:$E,$B30,'Transações'!$C:$C)) -> 0 | F30: =if(isblank($B30), "", D30-E30) -> 300 | K30: =if(isblank($H30), "", sumif('Transações'!$J:$J,$H30,'Transações'!$H:$H)) | L30: =if(isblank($H30), "", K30-J30)
B31: Internet | D31: 135 | E31: =if(isblank($B31), "", sumif('Transações'!$E:$E,$B31,'Transações'!$C:$C)) -> 0 | F31: =if(isblank($B31), "", D31-E31) -> 135
B32: Transporte | D32: 400 | E32: =if(isblank($B32), "", sumif('Transações'!$E:$E,$B32,'Transações'!$C:$C)) -> 0 | F32: =if(isblank($B32), "", D32-E32) -> 400
B33: Moradia | D33: 5500 | E33: =if(isblank($B33), "", sumif('Transações'!$E:$E,$B33,'Transações'!$C:$C)) -> 1100 | F33: =if(isblank($B33), "", D33-E33) -> 4400
B34: Celular | D34: 83 | E34: =if(isblank($B34), "", sumif('Transações'!$E:$E,$B34,'Transações'!$C:$C)) -> 0 | F34: =if(isblank($B34), "", D34-E34) -> 83
B35: Animais de estimação | D35: 600 | E35: =if(isblank($B35), "", sumif('Transações'!$E:$E,$B35,'Transações'!$C:$C)) -> 0 | F35: =if(isblank($B35), "", D35-E35) -> 600 | K35: =if(isblank($H35), "", sumif('Transações'!$J:$J,$H35,'Transações'!$H:$H)) | L35: =if(isblank($H35), "", K35-J35)
B36: Faxina | D36: 1600 | E36: =if(isblank($B36), "", sumif('Transações'!$E:$E,$B36,'Transações'!$C:$C)) -> 0 | F36: =if(isblank($B36), "", D36-E36) -> 1600 | K36: =if(isblank($H36), "", sumif('Transações'!$J:$J,$H36,'Transações'!$H:$H)) | L36: =if(isblank($H36), "", K36-J36)
B37: Seguro Carro | D37: 310 | E37: =if(isblank($B37), "", sumif('Transações'!$E:$E,$B37,'Transações'!$C:$C)) -> 0 | F37: =if(isblank($B37), "", D37-E37) -> 310 | K37: =if(isblank($H37), "", sumif('Transações'!$J:$J,$H37,'Transações'!$H:$H)) | L37: =if(isblank($H37), "", K37-J37)
B38: Assinaturas Mensais | D38: =sum(Assinaturas!B2:B8) -> 692 | E38: =if(isblank($B38), "", sumif('Transações'!$E:$E,$B38,'Transações'!$C:$C)) -> 0 | F38: =if(isblank($B38), "", D38-E38) -> 692 | K38: =if(isblank($H38), "", sumif('Transações'!$J:$J,$H38,'Transações'!$H:$H)) | L38: =if(isblank($H38), "", K38-J38)
B39: Assinaturas Anuais | D39: =SUM(Assinaturas!B11:B15)/12 -> 132.075 | E39: =if(isblank($B39), "", sumif('Transações'!$E:$E,$B39,'Transações'!$C:$C)) -> 0 | F39: =if(isblank($B39), "", D39-E39) -> 132.075
B40: Fretado | D40: 100 | E40: =if(isblank($B40), "", sumif('Transações'!$E:$E,$B40,'Transações'!$C:$C)) -> 0 | F40: =if(isblank($B40), "", D40-E40) -> 100 | K40: =if(isblank($H40), "", sumif('Transações'!$J:$J,$H40,'Transações'!$H:$H)) | L40: =if(isblank($H40), "", K40-J40)
B41: Isabel | D41: 500 | E41: =if(isblank($B41), "", sumif('Transações'!$E:$E,$B41,'Transações'!$C:$C)) -> 0 | F41: =if(isblank($B41), "", D41-E41) -> 500
E43: =if(isblank($B43), "", sumif('Transações'!$E:$E,$B43,'Transações'!$C:$C)) | F43: =if(isblank($B43), "", D43-E43) | K43: =if(isblank($H43), "", sumif('Transações'!$J:$J,$H43,'Transações'!$H:$H)) | L43: =if(isblank($H43), "", K43-J43)

Sheet Transações
B1: Para alterar ou adicionar categorias, atualize as tabelas "Despesas" e "Renda" na página "Resumo".
B2: Despesas | G2: Renda
B4: Data | C4: Valor | D4: Descrição | E4: Categoria | G4: Data | H4: Valor | I4: Descrição | J4: Categoria
B5: 36781 | C5: 1100 | D5: Aluguel | E5: Moradia | G5: 36781 | H5: 12418 | I5: Pagamento | J5: Pagamento

Sheet Assinaturas
A1: assinaturas
A2: chatgpt | B2: 100
A3: netflix | B3: 45
A4: contabilizei' | B4: 120
A5: youtube | B5: 54
A6: gympass | B6: 300
A7: google one | B7: 15
A8: copilot | B8: 58
A10: assinaturas anuais
A11: inshot | B11: 64.9
A12: lightroom | B12: 100
A13: faceapp | B13: 120
A14: facetune | B14: 300
A15: webdiet | B15: 1000
